port_scanner_fokd/__init__.py
port_scanner_fokd/port_scanner_fokd.py
port_scanner_fokd-0.2.0.dist-info/METADATA
port_scanner_fokd-0.2.0.dist-info/WHEEL
port_scanner_fokd-0.2.0.dist-info/licenses/LICENSE
port_scanner_fokd-0.2.0.dist-info/RECORD
